openapi_client/__init__.py
openapi_client/api_client.py
openapi_client/configuration.py
openapi_client/exceptions.py
openapi_client/model_utils.py
openapi_client/rest.py
openapi_client/api/__init__.py
openapi_client/api/default_api.py
openapi_client/apis/__init__.py
openapi_client/model/__init__.py
openapi_client/model/activation_params.py
openapi_client/model/add_custom_loss_params.py
openapi_client/model/add_custom_loss_response.py
openapi_client/model/add_dashboard_params.py
openapi_client/model/add_dataset_response.py
openapi_client/model/add_export_model_job_params.py
openapi_client/model/add_job_params.py
openapi_client/model/add_secret_manager_params.py
openapi_client/model/add_secret_manager_response.py
openapi_client/model/analyze_grad_type_enum.py
openapi_client/model/analyze_type_enum.py
openapi_client/model/analyzer_panel_layout.py
openapi_client/model/basic_visualization_info.py
openapi_client/model/cloud_provider.py
openapi_client/model/clusters.py
openapi_client/model/custom_loss.py
openapi_client/model/custom_loss_access.py
openapi_client/model/custom_loss_functions.py
openapi_client/model/custom_loss_list_response.py
openapi_client/model/custom_loss_version.py
openapi_client/model/dashboard.py
openapi_client/model/dashboard_type.py
openapi_client/model/data_state_type.py
openapi_client/model/data_type_enum.py
openapi_client/model/dataset.py
openapi_client/model/dataset_access.py
openapi_client/model/dataset_input_instance.py
openapi_client/model/dataset_input_type.py
openapi_client/model/dataset_metadata.py
openapi_client/model/dataset_metadata_instance.py
openapi_client/model/dataset_metadata_type.py
openapi_client/model/dataset_output_instance.py
openapi_client/model/dataset_output_type.py
openapi_client/model/dataset_parse_request_params.py
openapi_client/model/dataset_setup.py
openapi_client/model/dataset_subset_instance.py
openapi_client/model/dataset_version.py
openapi_client/model/delete_visualizations_params.py
openapi_client/model/demo.py
tensorleap_openapi_client-1.1.4.dist-info/METADATA
tensorleap_openapi_client-1.1.4.dist-info/WHEEL
tensorleap_openapi_client-1.1.4.dist-info/top_level.txt
tensorleap_openapi_client-1.1.4.dist-info/RECORD
